smarter/__init__.py
smarter/common.py
smarter/smartbool.py
smarter/smartdict.py
smarter/smartfloat.py
smarter/smartint.py
smarter/smartlist.py
smarter/smartnone.py
smarter/smartobject.py
smarter/smartset.py
smarter/smartstr.py
smarter/wrappers.py
smarter-0.1.4.dist-info/LICENSE
smarter-0.1.4.dist-info/METADATA
smarter-0.1.4.dist-info/WHEEL
smarter-0.1.4.dist-info/top_level.txt
smarter-0.1.4.dist-info/RECORD
