Metadata-Version: 2.1
Name: smarter
Version: 0.1.4
Summary: Some objects could be smarter
Home-page: UNKNOWN
Author: Bruno Rocha
License: UNKNOWN
Platform: UNKNOWN
Provides-Extra: test
Requires-Dist: pytest ; extra == 'test'
Requires-Dist: coverage ; extra == 'test'
Requires-Dist: flake8 ; extra == 'test'
Requires-Dist: black ; extra == 'test'
Requires-Dist: isort ; extra == 'test'
Requires-Dist: pytest-cov ; extra == 'test'
Requires-Dist: codecov ; extra == 'test'
Requires-Dist: mypy ; extra == 'test'
Requires-Dist: gitchangelog ; extra == 'test'
